imgdd-0.1.5.dist-info/METADATA
imgdd-0.1.5.dist-info/WHEEL
imgdd-0.1.5.dist-info/licenses/LICENSE
imgdd/__init__.py
imgdd/__init__.pyi
imgdd/py.typed
imgdd/imgdd.pyd
imgdd-0.1.5.dist-info/RECORD
